src/__main__.py
src/hackernewscli/__init__.py
src/hackernewscli/cache.py
src/hackernewscli/cli.py
src/hackernewscli/configs.py
src/hackernewscli/curl.py
src/hackernewscli/runner.py
hackernewscli_term-0.0.4.dist-info/METADATA
hackernewscli_term-0.0.4.dist-info/WHEEL
hackernewscli_term-0.0.4.dist-info/licenses/LICENSE
hackernewscli_term-0.0.4.dist-info/RECORD
