Metadata-Version: 2.1
Name: hackernewscli_term
Version: 0.0.4
Summary: hackernews in the cli
Project-URL: Homepage, https://github.com/rodfer0x80/hackernewscli
Project-URL: Bug Tracker, https://github.com/rodfer0x80/hackernewscli/issues
Author-email: rodfer0x80 <rodfer0x80@proton.me>
License:                     GNU GENERAL PUBLIC LICENSE
License-File: LICENSE
Classifier: License :: OSI Approved :: GNU General Public License v3 (GPLv3)
Classifier: Operating System :: POSIX
Classifier: Programming Language :: Python :: 3
Requires-Python: >=3.7
